klpmetrics/__init__.py
kglp_metrics-1.0.dist-info/LICENSE
kglp_metrics-1.0.dist-info/METADATA
kglp_metrics-1.0.dist-info/WHEEL
kglp_metrics-1.0.dist-info/top_level.txt
kglp_metrics-1.0.dist-info/RECORD
